<?xml version='1.0' standalone='yes'?>
<extensions>
  <plugins>
    <plugin maxTarget="*" version="0.0.0.47" minTarget="7.7" name="Twitch">
      <creator>bungh0l10</creator>
      <category>musicservices</category>
      <sha>ab2f530b3033b69b8886798f7e830466ca27111b</sha>
      <title lang="EN">Twitch</title>
      <desc lang="EN">Audio-only Twitch Streaming Plugin for LMS</desc>
      <url>https://github.com/bungh0l10/twitchaudio/releases/download/0.0.0.47/TWITCH.zip</url>
    </plugin>
  </plugins>
  <details>
    <title lang="EN">Mein Plugin-Repo</title>
  </details>
</extensions>
